pfeiffer_turbo/__init__.py
pfeiffer_turbo/device.py
pfeiffer_turbo/errors.py
pfeiffer_turbo/parameters.py
pfeiffer_turbo/telegram.py
pfeiffer_turbo-0.1.2.dist-info/LICENSE
pfeiffer_turbo-0.1.2.dist-info/WHEEL
pfeiffer_turbo-0.1.2.dist-info/METADATA
pfeiffer_turbo-0.1.2.dist-info/RECORD
