Metadata-Version: 2.1
Name: pfeiffer-turbo
Version: 0.1.2
Summary: 
Home-page: https://github.com/ograsdijk/pfeiffer-turbo
License: MIT
Author: ograsdijk
Author-email: o.grasdijk@gmail.com
Requires-Python: >=3.9,<4.0
Classifier: License :: OSI Approved :: MIT License
Classifier: Programming Language :: Python :: 3
Classifier: Programming Language :: Python :: 3.9
Classifier: Programming Language :: Python :: 3.10
Requires-Dist: PyVISA (>=1.13.0,<2.0.0)
Project-URL: Repository, https://github.com/ograsdijk/pfeiffer-turbo
